CHANGELOG.txt
CONTRIBUTORS.txt
LICENSE.txt
README.txt
TODO.txt
setup.cfg
setup.py
doc/registration.html
doc/style.css
registration/__init__.py
registration/release.py
registration.egg-info/PKG-INFO
registration.egg-info/SOURCES.txt
registration.egg-info/dependency_links.txt
registration.egg-info/entry_points.txt
registration.egg-info/not-zip-safe
registration.egg-info/requires.txt
registration.egg-info/top_level.txt
registration/ormmanager/__init__.py
registration/ormmanager/api.py
registration/ormmanager/sadispatch.py
registration/ormmanager/sodispatch.py
registration/ormmanager/tests/__init__.py
registration/ormmanager/tests/generic.py
registration/ormmanager/tests/samodel.py
registration/ormmanager/tests/somodel.py
registration/ormmanager/tests/testsa.py
registration/ormmanager/tests/testso.py
registration/template/+package+/config/registration.cfg
registration/template/+package+/registration/__init__.py
registration/template/+package+/registration/controllers.py_tmpl
registration/template/+package+/registration/model.py_tmpl
registration/template/+package+/registration/widgets.py_tmpl
registration/template/+package+/templates/registration/__init__.py
registration/template/+package+/templates/registration/changed_email.txt
registration/template/+package+/templates/registration/create.kid
registration/template/+package+/templates/registration/delete_user.kid
registration/template/+package+/templates/registration/edit_user.kid
registration/template/+package+/templates/registration/email_body_lost_password.txt
registration/template/+package+/templates/registration/email_body_new.txt
registration/template/+package+/templates/registration/email_body_reset_password.txt
registration/template/+package+/templates/registration/login.kid
registration/template/+package+/templates/registration/lost_password.kid
registration/template/+package+/templates/registration/new.kid
registration/template/+package+/templates/registration/recover_lost_password.kid
registration/template/+package+/templates/registration/tabletemplate.kid_tmpl
registration/template/+package+/templates/registration/validate.kid
registration/template/+package+/templates/registration/validate_email.kid
