Metadata-Version: 1.0
Name: registration
Version: 0.4
Summary: A set of TurboGears templates to provide user registration functions.
Home-page: http://patrickhlewis.googlepages.com/registration.html
Author: Patrick Lewis
Author-email: plewis@spamcop.net
License: MIT
Keywords: turbogears.quickstart.template
Platform: Any
Classifier: Development Status :: 4 - Beta
Classifier: Operating System :: OS Independent
Classifier: Programming Language :: Python
Classifier: Topic :: Software Development :: Libraries :: Python Modules
Classifier: Framework :: TurboGears
Classifier: License :: OSI Approved :: MIT License
